binjector/README.md
binjector/__init__.py
binjector/cli.py
binjector/steganography.py
binjector/utils.py
binjector-0.1.8.dist-info/LICENSE
binjector-0.1.8.dist-info/METADATA
binjector-0.1.8.dist-info/WHEEL
binjector-0.1.8.dist-info/entry_points.txt
binjector-0.1.8.dist-info/RECORD
