Metadata-Version: 2.1
Name: binjector
Version: 0.1.8
Summary: Binjector(Binary Injector) makes your text inject into image easily.
License: MIT
Author: d3fau1t
Author-email: aciddust20@gmail.com
Requires-Python: >=3.12,<4.0
Classifier: License :: OSI Approved :: MIT License
Classifier: Programming Language :: Python :: 3
Classifier: Programming Language :: Python :: 3.12
Classifier: Programming Language :: Python :: 3.13
Requires-Dist: click (>=8.1.8,<9.0.0)
Requires-Dist: numpy (>=2.2.2,<3.0.0)
Requires-Dist: pillow (>=11.1.0,<12.0.0)
